LilypondToBandVideoConverter-1.1.1.post1.data/data/Lib/site-packages/lilypondToBVC/LICENSE.txt
LilypondToBandVideoConverter-1.1.1.post1.data/data/Lib/site-packages/lilypondToBVC/lilypondToBandVideoConverter.pdf
LilypondToBandVideoConverter-1.1.1.post1.data/data/Lib/site-packages/lilypondToBVC/demo/demo.jpg
LilypondToBandVideoConverter-1.1.1.post1.data/data/Lib/site-packages/lilypondToBVC/demo/globalconfig-post.txt
LilypondToBandVideoConverter-1.1.1.post1.data/data/Lib/site-packages/lilypondToBVC/demo/globalconfig-pre.txt
LilypondToBandVideoConverter-1.1.1.post1.data/data/Lib/site-packages/lilypondToBVC/demo/wonderful_song-config.txt
LilypondToBandVideoConverter-1.1.1.post1.data/data/Lib/site-packages/lilypondToBVC/demo/wonderful_song-music.ly
lilypondtobvc/src/basemodules/__init__.py
lilypondtobvc/src/basemodules/attributemanager.py
lilypondtobvc/src/basemodules/configurationfile.py
lilypondtobvc/src/basemodules/datatypesupport.py
lilypondtobvc/src/basemodules/jsonfile.py
lilypondtobvc/src/basemodules/operatingsystem.py
lilypondtobvc/src/basemodules/regexppattern.py
lilypondtobvc/src/basemodules/simpleassertion.py
lilypondtobvc/src/basemodules/simplelogging.py
lilypondtobvc/src/basemodules/simpletypes.py
lilypondtobvc/src/basemodules/stringutil.py
lilypondtobvc/src/basemodules/tablefile.py
lilypondtobvc/src/basemodules/ttbase.py
lilypondtobvc/src/basemodules/typesupport.py
lilypondtobvc/src/basemodules/utf8file.py
lilypondtobvc/src/basemodules/validitychecker.py
lilypondtobvc/src/convertermodules/__init__.py
lilypondtobvc/src/convertermodules/audiotrackmanager.py
lilypondtobvc/src/convertermodules/lilypondfilegenerator.py
lilypondtobvc/src/convertermodules/lilypondpngvideogenerator.py
lilypondtobvc/src/convertermodules/ltbvc.py
lilypondtobvc/src/convertermodules/ltbvc_businesstypes.py
lilypondtobvc/src/convertermodules/ltbvc_configurationdatahandler.py
lilypondtobvc/src/convertermodules/midifilehandler.py
lilypondtobvc/src/convertermodules/miditransformer.py
LilypondToBandVideoConverter-1.1.1.post1.dist-info/LICENSE.txt
LilypondToBandVideoConverter-1.1.1.post1.dist-info/METADATA
LilypondToBandVideoConverter-1.1.1.post1.dist-info/WHEEL
LilypondToBandVideoConverter-1.1.1.post1.dist-info/entry_points.txt
LilypondToBandVideoConverter-1.1.1.post1.dist-info/top_level.txt
LilypondToBandVideoConverter-1.1.1.post1.dist-info/RECORD
