Metadata-Version: 2.1
Name: LilypondToBandVideoConverter
Version: 1.1.1.post1
Summary: Generator for Notation Videos from Lilypond Text
Home-page: https://github.com/prof-spock/LilypondToBandVideoConverter
Author: Dr. Thomas Tensi
Author-email: t.tensi@gmx.de
License: MIT
Keywords: video audio generation midi lilypond
Platform: UNKNOWN
Classifier: Development Status :: 5 - Production/Stable
Classifier: Environment :: Console
Classifier: Intended Audience :: End Users/Desktop
Classifier: Topic :: Multimedia :: Sound/Audio :: Conversion
Classifier: Topic :: Multimedia :: Video :: Conversion
Classifier: License :: OSI Approved :: MIT License
Classifier: Programming Language :: Python :: 3.7
Requires-Python: >=3.7, <4
Requires-Dist: mutagen
